joen_zz_mcp_demo/__init__.py
joen_zz_mcp_demo-0.1.0.dist-info/METADATA
joen_zz_mcp_demo-0.1.0.dist-info/WHEEL
joen_zz_mcp_demo-0.1.0.dist-info/entry_points.txt
joen_zz_mcp_demo-0.1.0.dist-info/RECORD
