Metadata-Version: 2.4
Name: joen-zz-mcp-demo
Version: 0.1.0
Summary: Add your description here
Author-email: zhaoxun <zhaoxun@acoinfo.com>
Requires-Python: >=3.13
Requires-Dist: mcp[cli]>=1.10.1
